{
    "countrys":[
        {
            "eng":"Afghanistan",
            "rus":"Афганистан"
        },
        {
            "eng":"Albania",
            "rus":"Албания"
        },
        {
            "eng":"Algeria",
            "rus":"Алжир"
        },
        {
            "eng":"Andorra",
            "rus":"Андорра"
        },
        {
            "eng":"Angola",
            "rus":"Ангола"
        },
        {
            "eng":"Antigua and Barbuda",
            "rus":"Антигуа и Барбуда"
        },
        {
            "eng":"Argentina",
            "rus":"Аргентина"
        },
        {
            "eng":"Armenia",
            "rus":"Армения"
        },
        {
            "eng":"Australia",
            "rus":"Австралия"
        },
        {
            "eng":"Austria",
            "rus":"Австрия"
        },
        {
            "eng":"Azerbaijan",
            "rus":"Азербайджан"
        },
        {
            "eng":"Bahamas",
            "rus":"Багамы"
        },
        {
            "eng":"Bahrain",
            "rus":"Бахрейн"
        },
        {
            "eng":"Bangladesh",
            "rus":"Бангладеш"
        },
        {
            "eng":"Barbados",
            "rus":"Барбадос"
        },
        {
            "eng":"Belarus",
            "rus":"Беларусь"
        },
        {
            "eng":"Belgium",
            "rus":"Бельгия"
        },
        {
            "eng":"Belize",
            "rus":"Белиз"
        },
        {
            "eng":"Benin",
            "rus":"Бенин"
        },
        {
            "eng":"Bhutan",
            "rus":"Bhutan"
        },
        {
            "eng":"Bolivia",
            "rus":"Боливия"
        },
        {
            "eng":"Bosnia and Herzegovina",
            "rus":"Босния и Герцеговина"
        },
        {
            "eng":"Botswana",
            "rus":"Ботсвана"
        },
        {
            "eng":"Brazil",
            "rus":"Бразилия"
        },
        {
            "eng":"Brunei",
            "rus":"Бруней"
        },
        {
            "eng":"Bulgaria",
            "rus":"Болгария"
        },
        {
            "eng":"Burkina Faso",
            "rus":"Буркина-Фасо"
        },
        {
            "eng":"Burundi",
            "rus":"Бурунди"
        },
        {
            "eng":"Côte d'Ivoire",
            "rus":"Берег Слоновой Кости"
        },
        {
            "eng":"Cabo Verde",
            "rus":"Кабо-Верде"
        },
        {
            "eng":"Cambodia",
            "rus":"Камбоджа"
        },
        {
            "eng":"Cameroon",
            "rus":"Камерун"
        },
        {
            "eng":"Canada",
            "rus":"Канада"
        },
        {
            "eng":"Central African Republic",
            "rus":"Центрально-Африканская Республика"
        },
        {
            "eng":"Chad",
            "rus":"Чад"
        },
        {
            "eng":"Chile",
            "rus":"Чили"
        },
        {
            "eng":"China",
            "rus":"Китай"
        },
        {
            "eng":"Austria",
            "rus":"Афганистан"
        },
        {
            "eng":"Colombia",
            "rus":"Колумбия"
        },
        {
            "eng":"Comoros",
            "rus":"Коморские острова"
        },
        {
            "eng":"Congo-Brazzaville",
            "rus":"Конго-Браззавиль"
        },
        {
            "eng":"Austria",
            "rus":"Афганистан"
        },
        {
            "eng":"Costa Rica",
            "rus":"Коста-Рика"
        },
        {
            "eng":"Croatia",
            "rus":"Хорватия"
        },
        {
            "eng":"Cuba",
            "rus":"Куба"
        },
        {
            "eng":"Cyprus",
            "rus":"Кипр"
        },
        {
            "eng":"Czechia",
            "rus":"Чехия"
        },
        {
            "eng":"Democratic Republic of the Congo",
            "rus":"Демократическая Республика Конго"
        },
        {
            "eng":"Denmark",
            "rus":"Дания"
        },
        {
            "eng":"Djibouti",
            "rus":"Джибути"
        },
        {
            "eng":"Dominica",
            "rus":"Доминика"
        },
        {
            "eng":"Dominican Republic",
            "rus":"Доминиканская Республика"
        },
        {
            "eng":"Ecuador",
            "rus":"Эквадор"
        },
        {
            "eng":"Egypt",
            "rus":"Египет"
        },
        {
            "eng":"El Salvador",
            "rus":"Сальвадор"
        },
        {
            "eng":"Equatorial Guinea",
            "rus":"Экваториальная Гвинея"
        },
        {
            "eng":"Eritrea",
            "rus":"Эритрея"
        },
        {
            "eng":"Estonia",
            "rus":"Эстония"
        },
        {
            "eng":"Eswatini",
            "rus":"Эсватини"
        },
        {
            "eng":"Ethiopia",
            "rus":"Эфиопия"
        },
        {
            "eng":"Fiji",
            "rus":"Фиджи"
        },
        {
            "eng":"Finland",
            "rus":"Финляндия"
        },
        {
            "eng":"France",
            "rus":"Франция"
        },
        {
            "eng":"Gabon",
            "rus":"Габон"
        },
        {
            "eng":"Gambia",
            "rus":"Гамбия"
        },
        {
            "eng":"Georgia",
            "rus":"Грузия   "
        },
        {
            "eng":"Germany",
            "rus":"Германия"
        },
        {
            "eng":"Ghana",
            "rus":"Гана"
        },
        {
            "eng":"Greece",
            "rus":"Греция"
        },
        {
            "eng":"Grenada",
            "rus":"Гренада"
        },
        {
            "eng":"Guatemala",
            "rus":"Гватемала"
        },
        {
            "eng":"Guinea",
            "rus":"Гвинея"
        },
        {
            "eng":"Guinea-Bissau",
            "rus":"Гвинея-Бисау"
        },
        {
            "eng":"Guyana",
            "rus":"Гайана"
        },
        {
            "eng":"Haiti",
            "rus":"Гаити"
        },
        {
            "eng":"Holy See",
            "rus":"Святой Престол"
        },
        {
            "eng":"Honduras",
            "rus":"Гондурас "
        },
        {
            "eng":"Hungary",
            "rus":"Венгрия"
        },
        {
            "eng":"Iceland",
            "rus":"Исландия"
        },
        {
            "eng":"India",
            "rus":"Индия"
        },
        {
            "eng":"Indonesia",
            "rus":"Индонезия"
        },
        {
            "eng":"Iran",
            "rus":"Iran"
        },
        {
            "eng":"Iraq",
            "rus":"Ирак"
        },
        {
            "eng":"Ireland",
            "rus":"Ирландия"
        },
        {
            "eng":"Israel",
            "rus":"Израиль"
        },
        {
            "eng":"Italy",
            "rus":"Италия"
        },
        {
            "eng":"Jamaica",
            "rus":"Ямайка"
        },
        {
            "eng":"Japan",
            "rus":"Япония"
        },
        {
            "eng":"Jordan",
            "rus":"Иордания"
        },
        {
            "eng":"Kazakhstan",
            "rus":"Казахстан"
        },
        {
            "eng":"Kenya",
            "rus":"Кения"
        },
        {
            "eng":"Kiribati",
            "rus":"Кирибати"
        },
        {
            "eng":"Kuwait",
            "rus":"Кувейт"
        },
        {
            "eng":"Kyrgyzstan",
            "rus":"Кыргызстан"
        },

        {
            "eng":"Laos",
            "rus":"Лаос"
        },
        {
            "eng":"Latvia",
            "rus":"Латвия"
        },
                {
            "eng":"Lebanon",
            "rus":"Ливан"
        },
        {
            "eng":"Lesotho",
            "rus":"Лесото"
        },
        {
            "eng":"Liberia",
            "rus":"Либерия"
        },

        {
            "eng":"Libya",
            "rus":"Ливия"
        },
        {
            "eng":"Liechtenstein",
            "rus":"Лихтенштейн"
        },
        {
            "eng":"Lithuania",
            "rus":"Литва"
        },        {
            "eng":"Luxembourg",
            "rus":"Люксембург"
        },
        {
            "eng":"Madagascar",
            "rus":"Мадагаскар"
        },
        {
            "eng":"Malawi",
            "rus":"Малави"
        },
        {
            "eng":"Malaysia",
            "rus":"Малайзия"
        },
        {
            "eng":"Maldives",
            "rus":"Мальдивы"
        },
        {
            "eng":"Mali",
            "rus":"Мали"
        },
        {
            "eng":"Malta",
            "rus":"Мальта"
        },
        {
            "eng":"Marshall Islands",
            "rus":"Маршалловы острова"
        },
        {
            "eng":"Mauritania",
            "rus":"Мавритания"
        },
        {
            "eng":"Mauritius",
            "rus":"Маврикий"
        },
        {
            "eng":"Mexico",
            "rus":"Мексика"
        },
        {
            "eng":"Micronesia",
            "rus":"Микронезия"
        },
        {
            "eng":"Moldova",
            "rus":"Молдавия"
        },
        {
            "eng":"Monaco",
            "rus":"Монако"
        },
        {
            "eng":"Mongolia",
            "rus":"Монголия"
        },
        {
            "eng":"Montenegro",
            "rus":"Черногория"
        },
        {
            "eng":"Morocco",
            "rus":"Марокко"
        },
        {
            "eng":"Mozambique",
            "rus":"Мозамбик"
        },
        {
            "eng":"Myanmar",
            "rus":"Мьянма"
        },
        {
            "eng":"Namibia",
            "rus":"Намибия"
        },
        {
            "eng":"Namibia",
            "rus":"Науру"
        },
        {
            "eng":"Nepal",
            "rus":"Непал"
        },
        {
            "eng":"Netherlands",
            "rus":"Нидерланды"
        },
        {
            "eng":"New Zealand",
            "rus":"Новая Зеландия"
        },
        {
            "eng":"Nicaragua",
            "rus":"Никарагуа"
        },
        {
            "eng":"Niger",
            "rus":"Нигер"
        },
        {
            "eng":"Nigeria",
            "rus":"Нигерия"
        },
        {
            "eng":"North Korea",
            "rus":"Северная Корея"
        },
        {
            "eng":"North Macedonia",
            "rus":"Северная Македония"
        },
        {
            "eng":"Norway",
            "rus":"Норвегия"
        },
        {
            "eng":"Oman",
            "rus":"Оман"
        },
        {
            "eng":"Pakistan",
            "rus":"Пакистан"
        },
        {
            "eng":"Palau",
            "rus":"Палау"
        },
        {
            "eng":"Palestine State",
            "rus":"Государство Палестина"
        },
        {
            "eng":"Panama",
            "rus":"Панама"
        },
        {
            "eng":"Papua New Guinea",
            "rus":"Папуа - Новая Гвинея"
        },
        {
            "eng":"Paraguay",
            "rus":"Парагвай"
        },
        {
            "eng":"Peru",
            "rus":"Перу"
        },
        {
            "eng":"Philippines",
            "rus":"Филиппины"
        },
        {
            "eng":"Poland",
            "rus":"Польша"
        },
        {
            "eng":"Portugal",
            "rus":"Португалия"
        },
        {
            "eng":"Qatar",
            "rus":"Катар"
        },
        {
            "eng":"Romania",
            "rus":"Румыния"
        },
        {
            "eng":"Russia",
            "rus":"Россия"
        },
        {
            "eng":"Rwanda",
            "rus":"Руанда"
        },
        {
            "eng":"Saint Kitts and Nevis ",
            "rus":"Сент-Китс и Невис"
        },
        {
            "eng":"Saint Lucia",
            "rus":"Санкт-Люсия"
        },
        {
            "eng":"Saint Vincent and the Grenadines",
            "rus":"Святой Винсент и Гренадины"
        },
        {
            "eng":"Samoa",
            "rus":"Самоа"
        },
        {
            "eng":"San Marino",
            "rus":"Сан-Марино"
        },
        {
            "eng":"Sao Tome and Principe",
            "rus":"Сан-Томе и Принсипи"
        },
        {
            "eng":"Saudi Arabia",
            "rus":"Саудовская Аравия"
        },
        {
            "eng":"Senegal",
            "rus":"Сенегал"
        },
        {
            "eng":"Serbia",
            "rus":"Сербия"
        },
        {
            "eng":"Seychelles",
            "rus":"Сейшельские острова"
        },
        {
            "eng":"Sierra Leone",
            "rus":"Сьерра-Леоне"
        },
        {
            "eng":"Singapore",
            "rus":"Сингапур"
        },
        {
            "eng":"Slovakia",
            "rus":"Словакия"
        },
        {
            "eng":"Slovenia",
            "rus":"Словения"
        },
        {
            "eng":"Solomon Islands",
            "rus":"Соломоновы острова"
        },
        {
            "eng":"Somalia",
            "rus":"Сомали"
        },
        {
            "eng":"South Africa",
            "rus":"Южная Африка"
        },
        {
            "eng":"South Korea",
            "rus":"Южная Корея"
        },
        {
            "eng":"South Sudan",
            "rus":"Южный Судан"
        },
        {
            "eng":"Spain",
            "rus":"Испания"
        },
        {
            "eng":"Sri Lanka",
            "rus":"Шри-Ланка"
        },
        {
            "eng":"Sudan",
            "rus":"Судан"
        },
        {
            "eng":"Suriname",
            "rus":"Суринам"
        },
        {
            "eng":"Sweden",
            "rus":"Швеция"
        },
        {
            "eng":"Switzerland",
            "rus":"Швейцария"
        },
        {
            "eng":"Syria",
            "rus":"Сирия"
        },
        {
            "eng":"Tajikistan",
            "rus":"Таджикистан"
        },
        {
            "eng":"Thailand",
            "rus":"Танзания"
        },
        {
            "eng":"Timor-Leste",
            "rus":"Восточный Тимор"
        },
        {
            "eng":"Togo",
            "rus":"Togo"
        },
        {
            "eng":"Tonga",
            "rus":"Тонга"
        },
        {
            "eng":"Trinidad and Tobago",
            "rus":"Тринидад и Тобаго"
        },
        {
            "eng":"Tunisia",
            "rus":"Тунис"
        },
        {
            "eng":"Turkey",
            "rus":"Турция"
        },
        {
            "eng":"Turkmenistan",
            "rus":"Туркменистан"
        },
        {
            "eng":"Tuvalu",
            "rus":"Тувалу"
        },
        {
            "eng":"Uganda",
            "rus":"Уганда"
        },
        {
            "eng":"Ukraine",
            "rus":"Украина"
        },
        {
            "eng":"United Arab Emirates",
            "rus":"Объединенные Арабские Эмираты"
        },
        {
            "eng":"United Kingdom",
            "rus":"Объединенное Королевство"
        },
        {
            "eng":"United States of America",
            "rus":"Соединенные Штаты Америки"
        },
        {
            "eng":"Uruguay",
            "rus":"Уругвай"
        },
        {
            "eng":"Uzbekistan",
            "rus":"Узбекистан"
        },
        {
            "eng":"Vanuatu",
            "rus":"Вануату"
        },
        {
            "eng":"Venezuela",
            "rus":"Венесуэла"
        },
        {
            "eng":"Vietnam",
            "rus":"Вьетнам"
        },
        {
            "eng":"Yemen",
            "rus":"Йемен"
        },
        {
            "eng":"Zambia",
            "rus":"Замбия"
        },
        {
            "eng":"Zimbabwe",
            "rus":"Зимбабве"
        }
    ],
    "week":[
        {
            "eng":["Monday","Tuesday","Wednesday","Thursday","Friday","Saturday","Sunday"],
            "rus":["Понедельник","Вторник","Среда","Четверг","Пятница","Суббота","Воскресенье"],
            "uzb":["Dushanba","Seshanba","Chorshanba","Payshanba","Juma","Shanba","Yakshanba"]
            
        }
    ],
    "month":[
        {
            "eng":["January","February","March","April","May","Jun","July","August","September","October","November","December"],
            "rus":["Январь","Февраль","Март","Апрель","Май","Июнь","Июль","Август","Сентябрь","Октябрь","Ноябрь","Декабрь"],
            "uzb":["Yanvar","Fevral","Mart","Aprel","May","Iyun","Iyul","Avgust","Sentabr","Oktabr","Noyabr","Dekabr"]
        }
    ]
}